tests/__init__.py
tests/conftest.py
tests/test_download.py
tests/test_microsoft_tts.py
tests/test_voice_parsing.py
wyoming_microsoft_tts/__init__.py
wyoming_microsoft_tts/__main__.py
wyoming_microsoft_tts/download.py
wyoming_microsoft_tts/handler.py
wyoming_microsoft_tts/microsoft_tts.py
wyoming_microsoft_tts/sentence_boundary.py
wyoming_microsoft_tts/version.py
wyoming_microsoft_tts/voices.json
wyoming_microsoft_tts-1.3.5.dist-info/METADATA
wyoming_microsoft_tts-1.3.5.dist-info/WHEEL
wyoming_microsoft_tts-1.3.5.dist-info/top_level.txt
wyoming_microsoft_tts-1.3.5.dist-info/RECORD
