Metadata-Version: 2.4
Name: wyoming-microsoft-tts
Version: 1.3.5
Summary: Add your description here
Home-page: https://github.com/hugobloem/wyoming-microsoft-tts
Author: Hugo Bloem
Author-email: 
Requires-Python: >=3.13
Requires-Dist: azure-cognitiveservices-speech>=1.45.0
Requires-Dist: black>=25.1.0
Requires-Dist: lxml>=6.0.1
Requires-Dist: pycountry>=24.6.1
Requires-Dist: regex>=2025.7.34
Requires-Dist: wyoming>=1.7.2
Dynamic: author
Dynamic: home-page
